{"job":{"content":[{"reader":{"name":"httpreader","parameter":{"column":[{"name":"name","type":"String"},{"name":"age","type":"int"}],"dataJosnPath":"data","httpMethod":"get","httpUrl":"","requestParam":[],"successCode":"200","successCodeJosnPath":"code"}},"writer":{"name":"hdfswriter","parameter":{"cloumn":[{"name":"name","type":"String"},{"name":"age","type":"int"}],"compress":"NONE","defaultFS":"hdfs://xxx:port","fieldDelimiter":"\t","fileName":"xxxxx","fileType":"orc","path":"/user/hive/warehouse/writerorc.db/orcfull","writeMode":"append"}}}],"setting":{"speed":{"channel":5}}}}
{"job":{"content":[{"reader":{"name":"httpreader","parameter":{"httpUrl":"","httpMethod":"get","requestParam":[],"successCode":"200","successCodeJosnPath":"code","dataJosnPath":"data","column":[{"name":"name","type":"String"},{"name":"age","type":"int"}]}},"writer":{"name":"hdfswriter","parameter":{"defaultFS":"hdfs://xxx:port","fileType":"orc","fileName":"xxxxx","cloumn":[{"name":"name","type":"String"},{"name":"age","type":"int"}],"writeMode":"append","fieldDelimiter":"\t","compress":"NONE","path":"/user/hive/warehouse/writerorc.db/orcfull"}}}],"setting":{"speed":{"channel":5}}}}
